{
    "10": {
        "id": 10,
        "islandPoints": -1
    },
    "100": {
        "id": 100,
        "islandPoints": 35
    },
    "101": {
        "id": 101,
        "islandPoints": 35
    },
    "102": {
        "id": 102,
        "islandPoints": 35
    },
    "103": {
        "id": 103,
        "islandPoints": 57
    },
    "104": {
        "id": 104,
        "islandPoints": 57
    },
    "105": {
        "id": 105,
        "islandPoints": 57
    },
    "106": {
        "id": 106,
        "islandPoints": 57
    },
    "107": {
        "id": 107,
        "islandPoints": 57
    },
    "108": {
        "id": 108,
        "islandPoints": 57
    },
    "109": {
        "id": 109,
        "islandPoints": 81
    },
    "11": {
        "id": 11,
        "islandPoints": -1
    },
    "110": {
        "id": 110,
        "islandPoints": 35
    },
    "117": {
        "id": 117,
        "islandPoints": 57
    },
    "118": {
        "id": 118,
        "islandPoints": 57
    },
    "12": {
        "id": 12,
        "islandPoints": -1
    },
    "13": {
        "id": 13,
        "islandPoints": -1
    },
    "14": {
        "id": 14,
        "islandPoints": -1
    },
    "15": {
        "id": 15,
        "islandPoints": -1
    },
    "16": {
        "id": 16,
        "islandPoints": -1
    },
    "17": {
        "id": 17,
        "islandPoints": -1
    },
    "18": {
        "id": 18,
        "islandPoints": -1
    },
    "19": {
        "id": 19,
        "islandPoints": -1
    },
    "2": {
        "id": 2,
        "islandPoints": -1
    },
    "20": {
        "id": 20,
        "islandPoints": -1
    },
    "21": {
        "id": 21,
        "islandPoints": -1
    },
    "22": {
        "id": 22,
        "islandPoints": -1
    },
    "23": {
        "id": 23,
        "islandPoints": -1
    },
    "24": {
        "id": 24,
        "islandPoints": -1
    },
    "25": {
        "id": 25,
        "islandPoints": -1
    },
    "26": {
        "id": 26,
        "islandPoints": 57
    },
    "260": {
        "id": 260,
        "islandPoints": 35
    },
    "263": {
        "id": 263,
        "islandPoints": 15
    },
    "265": {
        "id": 265,
        "islandPoints": 8
    },
    "266": {
        "id": 266,
        "islandPoints": 8
    },
    "267": {
        "id": 267,
        "islandPoints": 8
    },
    "27": {
        "id": 27,
        "islandPoints": 57
    },
    "270": {
        "id": 270,
        "islandPoints": 46
    },
    "274": {
        "id": 274,
        "islandPoints": -1
    },
    "278": {
        "id": 278,
        "islandPoints": 35
    },
    "28": {
        "id": 28,
        "islandPoints": 100
    },
    "30": {
        "id": 30,
        "islandPoints": 57
    },
    "31": {
        "id": 31,
        "islandPoints": 35
    },
    "32": {
        "id": 32,
        "islandPoints": 35
    },
    "33": {
        "id": 33,
        "islandPoints": 81
    },
    "34": {
        "id": 34,
        "islandPoints": 57
    },
    "36": {
        "id": 36,
        "islandPoints": 35
    },
    "37": {
        "id": 37,
        "islandPoints": 46
    },
    "38": {
        "id": 38,
        "islandPoints": 57
    },
    "39": {
        "id": 39,
        "islandPoints": 57
    },
    "40": {
        "id": 40,
        "islandPoints": 57
    },
    "41": {
        "id": 41,
        "islandPoints": 57
    },
    "42": {
        "id": 42,
        "islandPoints": 57
    },
    "43": {
        "id": 43,
        "islandPoints": 57
    },
    "44": {
        "id": 44,
        "islandPoints": 57
    },
    "45": {
        "id": 45,
        "islandPoints": 57
    },
    "46": {
        "id": 46,
        "islandPoints": 57
    },
    "47": {
        "id": 47,
        "islandPoints": 35
    },
    "48": {
        "id": 48,
        "islandPoints": 57
    },
    "49": {
        "id": 49,
        "islandPoints": 57
    },
    "5": {
        "id": 5,
        "islandPoints": -1
    },
    "50": {
        "id": 50,
        "islandPoints": 57
    },
    "51": {
        "id": 51,
        "islandPoints": 57
    },
    "52": {
        "id": 52,
        "islandPoints": 57
    },
    "53": {
        "id": 53,
        "islandPoints": 57
    },
    "54": {
        "id": 54,
        "islandPoints": 57
    },
    "55": {
        "id": 55,
        "islandPoints": 57
    },
    "56": {
        "id": 56,
        "islandPoints": 57
    },
    "57": {
        "id": 57,
        "islandPoints": 35
    },
    "58": {
        "id": 58,
        "islandPoints": 35
    },
    "59": {
        "id": 59,
        "islandPoints": 57
    },
    "60": {
        "id": 60,
        "islandPoints": 57
    },
    "61": {
        "id": 61,
        "islandPoints": 57
    },
    "62": {
        "id": 62,
        "islandPoints": 35
    },
    "63": {
        "id": 63,
        "islandPoints": 57
    },
    "64": {
        "id": 64,
        "islandPoints": 35
    },
    "65": {
        "id": 65,
        "islandPoints": 57
    },
    "66": {
        "id": 66,
        "islandPoints": 57
    },
    "67": {
        "id": 67,
        "islandPoints": 35
    },
    "68": {
        "id": 68,
        "islandPoints": 81
    },
    "69": {
        "id": 69,
        "islandPoints": 57
    },
    "7": {
        "id": 7,
        "islandPoints": -1
    },
    "70": {
        "id": 70,
        "islandPoints": 100
    },
    "71": {
        "id": 71,
        "islandPoints": 57
    },
    "72": {
        "id": 72,
        "islandPoints": 57
    },
    "73": {
        "id": 73,
        "islandPoints": 57
    },
    "74": {
        "id": 74,
        "islandPoints": 57
    },
    "75": {
        "id": 75,
        "islandPoints": 57
    },
    "76": {
        "id": 76,
        "islandPoints": 57
    },
    "77": {
        "id": 77,
        "islandPoints": 46
    },
    "78": {
        "id": 78,
        "islandPoints": 57
    },
    "79": {
        "id": 79,
        "islandPoints": 57
    },
    "8": {
        "id": 8,
        "islandPoints": -1
    },
    "80": {
        "id": 80,
        "islandPoints": 57
    },
    "81": {
        "id": 81,
        "islandPoints": 57
    },
    "82": {
        "id": 82,
        "islandPoints": 57
    },
    "83": {
        "id": 83,
        "islandPoints": 57
    },
    "84": {
        "id": 84,
        "islandPoints": 57
    },
    "85": {
        "id": 85,
        "islandPoints": 57
    },
    "86": {
        "id": 86,
        "islandPoints": 57
    },
    "87": {
        "id": 87,
        "islandPoints": 57
    },
    "88": {
        "id": 88,
        "islandPoints": 57
    },
    "89": {
        "id": 89,
        "islandPoints": 57
    },
    "9": {
        "id": 9,
        "islandPoints": -1
    },
    "90": {
        "id": 90,
        "islandPoints": 57
    },
    "91": {
        "id": 91,
        "islandPoints": 57
    },
    "92": {
        "id": 92,
        "islandPoints": 57
    },
    "93": {
        "id": 93,
        "islandPoints": 57
    },
    "94": {
        "id": 94,
        "islandPoints": 45
    },
    "95": {
        "id": 95,
        "islandPoints": 100
    },
    "96": {
        "id": 96,
        "islandPoints": 81
    },
    "97": {
        "id": 97,
        "islandPoints": 57
    },
    "98": {
        "id": 98,
        "islandPoints": 57
    },
    "99": {
        "id": 99,
        "islandPoints": 45
    }
}
